ghcls/__init__.py
ghcls/__main__.py
ghcls/ghcls.py
ghcls/extensions/__init__.py
ghcls/extensions/linguist.py
github_commit_line_stats-1.2.2.dist-info/METADATA
github_commit_line_stats-1.2.2.dist-info/WHEEL
github_commit_line_stats-1.2.2.dist-info/top_level.txt
github_commit_line_stats-1.2.2.dist-info/RECORD
