Metadata-Version: 2.4
Name: github-commit-line-stats
Version: 1.2.2
Summary: Count how many lines of code you commit on GitHub! (Count by file extension)
Author-email: yindaheng98 <yindaheng98@gmail.com>
Project-URL: Homepage, https://github.com/yindaheng98/github-commit-line-stats
Classifier: Programming Language :: Python :: 3
Requires-Python: >=3.13
Requires-Dist: PyGithub
Provides-Extra: linguist
Requires-Dist: requests; extra == "linguist"
Requires-Dist: pyyaml; extra == "linguist"
